onlaw_api_client/__init__.py
onlaw_api_client/client.py
onlaw_api_client/prismaclient.py
onlaw_api_client-0.1.13.dist-info/LICENSE
onlaw_api_client-0.1.13.dist-info/METADATA
onlaw_api_client-0.1.13.dist-info/WHEEL
onlaw_api_client-0.1.13.dist-info/top_level.txt
onlaw_api_client-0.1.13.dist-info/RECORD
