Metadata-Version: 2.1
Name: onlaw-api-client
Version: 0.1.13
Summary: client for api.onlaw.dk
Home-page: https://github.com/Onlaw/onlaw_api_client
Author: Onlaw
Author-email: jens@onlaw.dk
License: UNKNOWN
Platform: UNKNOWN
Classifier: Programming Language :: Python :: 3
Classifier: Operating System :: OS Independent
Requires-Dist: aiohttp
Requires-Dist: asyncio
Requires-Dist: auth0-python
Requires-Dist: pyjwt
